mgraphql/__init__.py
mgraphql/mgraphql.py
mgraphql-0.0.5.dist-info/METADATA
mgraphql-0.0.5.dist-info/WHEEL
mgraphql-0.0.5.dist-info/top_level.txt
mgraphql-0.0.5.dist-info/RECORD
