Metadata-Version: 2.1
Name: mgraphql
Version: 0.0.5
Summary: Python library link with graphql
Home-page: https://github.com/mahekan/mgraphql
Author: ayaz abdi
Author-email: mayazabdi@gmail.com
License: UNKNOWN
Platform: UNKNOWN
Classifier: Programming Language :: Python :: 3.8
Classifier: License :: OSI Approved :: GNU General Public License v3 (GPLv3)
Requires-Dist: requests (>=2)
